snns/__init__.py
snns-0.0.0.dist-info/METADATA
snns-0.0.0.dist-info/WHEEL
snns-0.0.0.dist-info/top_level.txt
snns-0.0.0.dist-info/RECORD
