Metadata-Version: 2.1
Name: snns
Version: 0.0.0
Summary: Description of my package
Home-page: https://open-neuromorphic.org
Author: Author Name
Author-email: author@gmail.com
